<?xml version='1.0' encoding='UTF-8'?>
<vx:AlimentaIO
  xmlns:vx='http://www.viaexpress.com.br/external/ViaExpress_external_integra.xsd'
  xmlns:xsi='http://www.w3.org/2001/XMLSchema-instance'>
  <vx:ticket>
    <vx:pid>AJURI</vx:pid>
    <vx:nome>AJURI</vx:nome>
    <vx:empresa>RV</vx:empresa>
    <vx:fornecedor>AJURI</vx:fornecedor>
    <vx:host>200.208.181.15</vx:host>
    <vx:data-origem>2016-04-25T12:53:30</vx:data-origem>
    <vx:versao>1.0.0</vx:versao>
    <vx:observacoes></vx:observacoes>
    <vx:id>123</vx:id>
    <vx:filial>
      <vx:codigo>vx:codigo</vx:codigo>
      <vx:documento-federal>05.366.444/0003-20</vx:documento-federal>
      <vx:razao-social>vx:razao-social</vx:razao-social>
    </vx:filial>
  </vx:ticket>
  <vx:documentos>
    <vx:documento tipo="ENTRADA">
      <vx:filial>
        <vx:codigo></vx:codigo>
        <vx:documento-federal>05.366.444/0003-20</vx:documento-federal>
        <vx:razao-social></vx:razao-social>
      </vx:filial>
      <vx:cabecalho-chave>
        <vx:cliente>
          <vx:documento-federal>00.697.295/0001-05</vx:documento-federal>
          <vx:razao-social></vx:razao-social>
        </vx:cliente>
        <vx:divisao-chave>NF</vx:divisao-chave>
        <vx:numero>0000159461</vx:numero>
        <vx:data>2016-04-04</vx:data>
        <vx:hora>12:30:53</vx:hora>
        <vx:serie>.</vx:serie>
        <vx:cfop>
          <vx:codigo>1000</vx:codigo>
          <vx:descricao></vx:descricao>
        </vx:cfop>
      </vx:cabecalho-chave>
      <vx:cabecalho>
        <vx:entidade>
          <vx:tipo>JURIDICA</vx:tipo>
          <vx:documento-federal>20.000.000/0458-30</vx:documento-federal>
          <vx:documento-estadual>20.000.000/0458-30</vx:documento-estadual>
          <vx:documento-municipal>20.000.000/0458-30</vx:documento-municipal>
          <vx:razao>BAXTER HOSPITALAR LTDA</vx:razao>
          <vx:fantasia>BAXTER</vx:fantasia>
          <vx:endereco>
            <vx:tipo>COMERCIAL</vx:tipo>
            <vx:cep>00.000-000</vx:cep>
            <vx:logradouro-tipo></vx:logradouro-tipo>
            <vx:logradouro>N/A</vx:logradouro>
            <vx:numero>0</vx:numero>
            <vx:bairro>N/A</vx:bairro>
            <vx:cidade>N/A</vx:cidade>
            <vx:uf>NA</vx:uf>
          </vx:endereco>
          <vx:is-cliente>NAO</vx:is-cliente>
          <vx:is-fornecedor>SIM</vx:is-fornecedor>
          <vx:is-fabricante>NAO</vx:is-fabricante>
          <vx:is-destinatario>NAO</vx:is-destinatario>
          <vx:observacoes></vx:observacoes>
          <vx:livres>
            <vx:livre>
              <vx:indice>6</vx:indice>
              <vx:nome>ID_AJURI</vx:nome>
              <vx:valor>45830</vx:valor>
            </vx:livre>
          </vx:livres>
        </vx:entidade>
        <vx:divisao-infomativa>NF</vx:divisao-infomativa>
        <vx:numero>0000159461</vx:numero>
        <vx:data>2016-04-04</vx:data>
        <vx:hora>12:30:53</vx:hora>
        <vx:serie>.</vx:serie>
        <vx:cfop>
          <vx:codigo>1000</vx:codigo>
          <vx:descricao></vx:descricao>
        </vx:cfop>
      </vx:cabecalho>
      <vx:observacoes></vx:observacoes>
      <vx:itens>
        <vx:item>
          <vx:produto>
            <vx:partnumber>63504</vx:partnumber>
          </vx:produto>
          <vx:quantidade-unidades>1</vx:quantidade-unidades>
          <vx:valor-unitario>1791.56</vx:valor-unitario>
          <vx:serial>2474</vx:serial>
        </vx:item>
      </vx:itens>
      <vx:livres>
        <vx:livre>
          <vx:indice>6</vx:indice>
          <vx:nome>TRANSACAO_ID_AJURI</vx:nome>
          <vx:valor>159461</vx:valor>
        </vx:livre>
        <vx:livre>
          <vx:indice>7</vx:indice>
          <vx:nome>TRANSACAO_ID_CLIENTE</vx:nome>
          <vx:valor>26</vx:valor>
        </vx:livre>
        <vx:livre>
          <vx:indice>3</vx:indice>
          <vx:nome>NUMERO_DOCUMENTO</vx:nome>
          <vx:valor>449634</vx:valor>
        </vx:livre>
      </vx:livres>
    </vx:documento>
  </vx:documentos>
</vx:AlimentaIO>